LICENSE
README.md
setup.cfg
setup.py
boost_colab/__init__.py
boost_colab/__main__.py
boost_colab.egg-info/PKG-INFO
boost_colab.egg-info/SOURCES.txt
boost_colab.egg-info/dependency_links.txt
boost_colab.egg-info/requires.txt
boost_colab.egg-info/top_level.txt